palpable/__init__.py
palpable/basis/__init__.py
palpable/basis/immutable.py
palpable/basis/setup_logger.py
palpable/basis/timestamped_immutable.py
palpable/procedures/__init__.py
palpable/procedures/map_function.py
palpable/procedures/procedure.py
palpable/procedures/run_function.py
palpable/servants/__init__.py
palpable/servants/manager.py
palpable/servants/servant.py
palpable/servants/server.py
palpable/servants/worker.py
palpable/units/__init__.py
palpable/units/client.py
palpable/units/messenger.py
palpable/units/result_cache.py
palpable/units/task.py
palpable/units/task_exceptions.py
palpable/units/task_queue.py
palpable/units/task_response.py
palpable/units/task_result.py
palpable-0.0.11.dist-info/LICENSE
palpable-0.0.11.dist-info/METADATA
palpable-0.0.11.dist-info/WHEEL
palpable-0.0.11.dist-info/top_level.txt
palpable-0.0.11.dist-info/RECORD
