Metadata-Version: 2.1
Name: palpable
Version: 0.0.11
Summary: A multiprocessing task server
Home-page: https://github.com/XiaoMutt/palpable
Author: Xiao
License: MIT
Platform: UNKNOWN
Classifier: License :: OSI Approved :: MIT License
Classifier: Programming Language :: Python :: 3
Classifier: Programming Language :: Python :: 3.7
Classifier: Programming Language :: Python :: 3.8
Classifier: Programming Language :: Python :: 3.8
Classifier: Programming Language :: Python :: 3.9
Classifier: Programming Language :: Python :: 3.10
Classifier: Programming Language :: Python :: 3 :: Only
License-File: LICENSE
Requires-Dist: dill
Requires-Dist: sortedcontainers
Requires-Dist: psutil
